{
  "code": 0,
  "message":"成功",
  "result":{
    "list":[{
      "id":1,
      "store": "572457fghf",
      "provider":"心中有梦闯天下",
      "company":"笑 就歌颂 一皱眉头就心痛",
      "address":"我这颗小星球 就在你手中转动",
      "sex":"0",
      "type":"衣服",
      "sort":"46",
      "createTime": "2016-09-08",
      "lastLoginTime": "2016-12-15",
      "telePhone":"13236549624",
      "logoImage":"../../images/unlogin.png",
      "birthday":"1988-10-10",
      "loginCount":"5",
      "userType":"0",
      "state":"0",
      "isEnabled":"1",
      "user":"0",
      "password":"2514646"
    },{
      "id":2,
      "store": "53685685",
      "provider":"好朋友的话要记在心里呀",
      "company":"你要往哪走 把我灵魂也带走",
      "address":"请 看见我 让我有梦可以做",
      "sex":"1",
      "type":"饮料",
      "sort":"245",
      "createTime": "2016-09-09",
      "lastLoginTime": "2016-11-11",
      "telePhone":"13005362468",
      "logoImage":"../../images/unlogin.png",
      "birthday":"1985-12-23",
      "loginCount":"24",
      "userType":"1",
      "state":"1",
      "isEnabled":"1",
      "user":"1",
      "password":"3gfjwt56"
    },{
      "id":3,
      "store": "时间追不上白马",
      "provider":"时间都去哪儿了",
      "company":"你是电 你是光 你是唯一的神话",
      "address":"你要往哪走 把我灵魂也带走",
      "sex":"1",
      "type":"数码",
      "sort":"835",
      "createTime": "2016-08-07",
      "lastLoginTime": "2016-09-27",
      "telePhone":"13197648468",
      "logoImage":"../../images/unlogin.png",
      "birthday":"1992-03-26",
      "loginCount":"346",
      "userType":"1",
      "state":"1",
      "isEnabled":"0",
      "user":"1",
      "password":"6254745"
    },{
      "id":4,
      "store": "小雨它拍打着水花",
      "provider":"有几滴眼泪在落下",
      "company":"手 不是手 是温柔的宇宙",
      "address":"我没空理会我 只感受你的感受",
      "sex":"0",
      "type":"电器",
      "sort":"36",
      "createTime": "2016-05-25",
      "lastLoginTime": "2016-05-26",
      "telePhone":"13513466582",
      "logoImage":"../../images/unlogin.png",
      "birthday":"1996-01-13",
      "loginCount":"825",
      "userType":"0",
      "state":"2",
      "isEnabled":"0",
      "user":"0",
      "password":"1564566"
    },{
      "id":5,
      "store": "在阳光灿烂日子开怀大笑",
      "provider":"也许当时忙着微笑和哭泣",
      "company":"火 你是火 是我飞蛾的尽头",
      "address":"你主宰 我崇拜 没有更好的办法",
      "sex":"0",
      "type":"帽子",
      "sort":"368",
      "createTime": "2016-12-13",
      "lastLoginTime": "2016-03-19",
      "telePhone":"15883575994",
      "logoImage":"../../images/unlogin.png",
      "birthday":"1982-09-29",
      "loginCount":"825",
      "userType":"0",
      "state":"0",
      "isEnabled":"1",
      "user":"0",
      "password":"247vj4572"
    }]
  }
}